pattern_feedback_tool/__init__.py
pattern_feedback_tool/doit_tasks.py
pattern_feedback_tool/graphics.py
pattern_feedback_tool/lint_parsers.py
pattern_feedback_tool/linters.py
pattern_feedback_tool/settings.py
pattern_feedback_tool-0.3.13.dist-info/LICENSE
pattern_feedback_tool-0.3.13.dist-info/WHEEL
pattern_feedback_tool-0.3.13.dist-info/METADATA
pattern_feedback_tool-0.3.13.dist-info/RECORD
